CHANGES.rst
MANIFEST.in
Makefile
Makefile.release
README.rst
setup.py
version.txt
src/metapensiero.tool.banner.egg-info/PKG-INFO
src/metapensiero.tool.banner.egg-info/SOURCES.txt
src/metapensiero.tool.banner.egg-info/dependency_links.txt
src/metapensiero.tool.banner.egg-info/entry_points.txt
src/metapensiero.tool.banner.egg-info/namespace_packages.txt
src/metapensiero.tool.banner.egg-info/requires.txt
src/metapensiero.tool.banner.egg-info/top_level.txt
src/metapensiero/tool/banner/__init__.py