Metadata-Version: 1.1
Name: metapensiero.tool.banner
Version: 0.1
Summary: Minimalistic SysV banner tool
Home-page: https://gitlab.com/metapensiero/metapensiero.tool.banner.git
Author: Lele Gaifax
Author-email: lele@metapensiero.it
License: GPLv3+
Platform: UNKNOWN
Classifier: Development Status :: 2 - Pre-Alpha
Classifier: Programming Language :: Python
Classifier: Programming Language :: Python :: 3
Classifier: Programming Language :: Python :: 3.5
Classifier: Programming Language :: Python :: 3.6
